{
  "User": {
     "username": {
    "string": [
      "pfesa",
      "admin"
    ]
  },
        "companyName": {
    "string": [
      "NEPTUNIA S.A.",
      "APM TERMINALS"
    ]
  },
    "company": {
    "string": [
      "20104582359",
      "20104523154"
    ]
  },
    "name": {
    "string": [
      "Thor",
      "Loki"
    ]
  },
   "token": {
    "string": [
      "3894ujgrsdfjpwy578",
      "aldsfj39845y9345ys"
    ]
  },
      "id": {
    "int": [
      1,
      2
    ]
  }
  },

  "Menu": {
    "name": {
    "string": [
      "Option 1",
      "Oprtion 2",
      "Option 3"
    ]
  },
  "url": {
    "string": [
      "/home",
      "/example_search"
    ]
  },
   "icon": {
    "string": [
      "home_outlined",
      "notifications_outlined"
    ]
  }
  }
  
  
   "Parameter": {
    "code": {
    "string": [
      "SECURITY-SERVICE",
      "PFE-API"
    ]
  },
  "value": {
    "string": [
      "http://localhost:1020/",
      "http://localhost:2820/"
    ]
  }
  }


}
